setup.py
basicpublisher/__init__.py
basicpublisher/publisher.py
basicpublisher.egg-info/PKG-INFO
basicpublisher.egg-info/SOURCES.txt
basicpublisher.egg-info/dependency_links.txt
basicpublisher.egg-info/not-zip-safe
basicpublisher.egg-info/requires.txt
basicpublisher.egg-info/top_level.txt