Metadata-Version: 1.0
Name: basicpublisher
Version: 0.1
Summary: publisher class for basic publisher-subscriber API
Home-page: https://github.com/geraldzakwan/Basic-Publish-Subscribe-API
Author: Geraldi Dzakwan
Author-email: geraldi.dzakwan@gmail.com
License: MIT
Platform: UNKNOWN
